{
    "type": {
        "client_type": "CONFIDENTIAL",
        "authority_type": "SINGLE_TENANT",
        "framework": "DJANGO"
    },
    "client": {
        "client_id": "5451bec6-4200-4326-99dc-fea4c8fb8be8",
        "client_credential": "2vM8Q~~0XN7Yxc.h1pka9G1qaPPXwEJEvfoPdbds",
        "authority": "https://login.microsoftonline.com/{846f6db3-c6a6-4131-b084-cf6b63ab8af5}"
    },
    "auth_request": {
        "redirect_uri": null,
        "scopes": [],
        "response_type": "code"
    },
    "flask": null,
    "django": {
        "id_web_configs": "MS_ID_WEB_CONFIGS",
        "auth_endpoints": {
            "prefix": "auth",
            "sign_in": "sign_in",
            "edit_profile": "edit_profile",
            "redirect": "redirect",
            "sign_out": "sign_out",
            "post_sign_out": "post_sign_out"
        }
    }
}